api_collection/__init__.py
api_collection/api_collection.py
api_collection/bilibili.py
api_collection/blocks.py
api_collection/example/apiWithTool.yaml
api_collection/example/parseUrl.yaml
chatgpt_mirai_qq_bot_api_collection-0.3.3.dist-info/LICENSE
chatgpt_mirai_qq_bot_api_collection-0.3.3.dist-info/METADATA
chatgpt_mirai_qq_bot_api_collection-0.3.3.dist-info/WHEEL
chatgpt_mirai_qq_bot_api_collection-0.3.3.dist-info/entry_points.txt
chatgpt_mirai_qq_bot_api_collection-0.3.3.dist-info/top_level.txt
chatgpt_mirai_qq_bot_api_collection-0.3.3.dist-info/RECORD
