Metadata-Version: 2.1
Name: chatgpt-mirai-qq-bot-api-collection
Version: 0.3.3
Summary: ApiCollectionPlugin for lss233/chatgpt-mirai-qq-bot
Home-page: https://github.com/chuanSir123/api_collection
Author: chuanSir
Author-email: 416448943@qq.com
Project-URL: Bug Tracker, https://github.com/chuanSir123/api_collection/issues
Project-URL: Documentation, https://github.com/chuanSir123/api_collection/wiki
Project-URL: Source Code, https://github.com/chuanSir123/api_collection
Classifier: Programming Language :: Python :: 3
Classifier: License :: OSI Approved :: GNU Affero General Public License v3
Classifier: Operating System :: OS Independent
Requires-Python: >=3.8
License-File: LICENSE
Requires-Dist: kirara-ai>=3.2.0
